beggs_and_brill_MatheusDelduque
