Metadata-Version: 2.1
Name: beggs-and-brill
Version: 0.0.6
Summary: Funções para beggs and brill
Author: Matheus Delduque
Author-email: matheusdelduque1@gmail.com
License: MIT License
Keywords: begss and brill
License-File: LICENSE
